gesichtfinder/README.MD
gesichtfinder/__init__.py
gesichtfinder/requirements.txt
gesichtfinder/thirdparty.json
gesichtfinder-0.10.dist-info/LICENSE.rst
gesichtfinder-0.10.dist-info/METADATA
gesichtfinder-0.10.dist-info/WHEEL
gesichtfinder-0.10.dist-info/top_level.txt
gesichtfinder-0.10.dist-info/RECORD
