Metadata-Version: 2.1
Name: gesichtfinder
Version: 0.10
Summary: Extracts faces from an image using different backend detectors and save the results in a DataFrame.
Home-page: https://github.com/hansalemaos/gesichtfinder
Author: Johannes Fischer
Author-email: aulasparticularesdealemaosp@gmail.com
License: MIT
Keywords: extract,faces
Classifier: Development Status :: 4 - Beta
Classifier: Programming Language :: Python :: 3 :: Only
Classifier: Programming Language :: Python :: 3.10
Classifier: Topic :: Software Development :: Libraries :: Python Modules
Classifier: Topic :: Utilities
License-File: LICENSE.rst
Requires-Dist: a-cv-imwrite-imread-plus
Requires-Dist: deepface
Requires-Dist: pandas
